setup.py
alabama/__init__.py
alabama/connection.py
alabama/enum.py
alabama/models.py
alabama/properties.py
alabama/query.py
alabama/storage.py
alabama.egg-info/PKG-INFO
alabama.egg-info/SOURCES.txt
alabama.egg-info/dependency_links.txt
alabama.egg-info/requires.txt
alabama.egg-info/top_level.txt
tests/__init__.py
tests/mock.py
tests/run_tests.py
tests/test_api.py
tests/test_connection_db.py
tests/test_enum.py
tests/test_metaclass.py
tests/test_model.py
tests/test_property.py
tests/test_query.py