Metadata-Version: 1.1
Name: alabama
Version: 0.1.4
Summary: A small and simple python orm to connect with postgresql database.
Home-page: http://github.com/felipevolpone/alabama_orm
Author: Felipe Volpone
Author-email: felipevolpone@gmail.com
License: MIT
Keywords: orm postgresql alabama
Platform: UNKNOWN
Classifier: Development Status :: 3 - Alpha
Classifier: Topic :: Utilities
